ardexa_check_active.py
ardexa_check_active-1.0.0.dist-info/DESCRIPTION.rst
ardexa_check_active-1.0.0.dist-info/METADATA
ardexa_check_active-1.0.0.dist-info/RECORD
ardexa_check_active-1.0.0.dist-info/WHEEL
ardexa_check_active-1.0.0.dist-info/entry_points.txt
ardexa_check_active-1.0.0.dist-info/metadata.json
ardexa_check_active-1.0.0.dist-info/top_level.txt
